data_element_extractor/__init__.py
data_element_extractor/categories.py
data_element_extractor/cde_server_service.py
data_element_extractor/config.py
data_element_extractor/extractor.py
data_element_extractor/helpers.py
data_element_extractor/inference_server.py
data_element_extractor/inference_server_service.py
data_element_extractor/model_answers.py
data_element_extractor/models.py
data_element_extractor/number_logits_processor.py
data_element_extractor/persistence.py
data_element_extractor/prompt_optimizer.py
data_element_extractor/prompts.py
data_element_extractor/table_extractor.py
data_element_extractor/topics.py
data_element_extractor/ui.py
data_element_extractor/ui/__init__.py
data_element_extractor/ui/extractor_view.py
data_element_extractor/ui/main_app.py
data_element_extractor/ui/menu_bar.py
data_element_extractor/ui/model_config_view.py
data_element_extractor/ui/think_config_view.py
data_element_extractor/ui/topics_view.py
data_element_extractor/ui/ui_helpers.py
data_element_extractor-0.0.1.dist-info/licenses/LICENSE
data_element_extractor-0.0.1.dist-info/METADATA
data_element_extractor-0.0.1.dist-info/WHEEL
data_element_extractor-0.0.1.dist-info/top_level.txt
data_element_extractor-0.0.1.dist-info/RECORD
