Metadata-Version: 2.4
Name: data_element_extractor
Version: 0.0.1
Summary: This python package is designed to provide an adaptable framework for data extraction. It can be used to manage and extract data from text across multiple topics using Large Language Models (LLMs).
Author-email: Fabio Dennstädt <fabiodennstaedt@gmx.de>
Classifier: Programming Language :: Python :: 3
Classifier: Operating System :: OS Independent
Classifier: License :: OSI Approved :: MIT License
Requires-Python: >=3.7
License-File: LICENSE
Dynamic: license-file
